rony/__init__.py
rony/_version.py
rony/cli.py
rony/cli_aux.py
rony/module_writer.py
rony/validation.py
rony/module_templates/CI_workflows.json
rony/module_templates/__AWS_BASE__.json
rony/module_templates/__GCP_BASE__.json
rony/module_templates/aws_glue_crawler.json
rony/module_templates/aws_glue_job.json
rony/module_templates/aws_lambda_function.json
rony/module_templates/aws_simple_storage_service.json
rony/module_templates/gcp_bigquery.json
rony/module_templates/gcp_cloud_function.json
rony/module_templates/gcp_cloud_storage.json
rony/module_templates/gcp_pubsub.json
rony/module_templates/CI_workflows/.gitignore
rony/module_templates/CI_workflows/.gitlab-ci.yml
rony/module_templates/CI_workflows/.tpl.env
rony/module_templates/CI_workflows/Makefile
rony/module_templates/CI_workflows/bitbucket-pipelines.yml
rony/module_templates/CI_workflows/.github/workflows/production.yml
rony/module_templates/CI_workflows/.github/workflows/production_destroy.yml
rony/module_templates/CI_workflows/.github/workflows/staging.yml
rony/module_templates/CI_workflows/.github/workflows/staging_destroy.yml
rony/module_templates/CI_workflows/.github/workflows/test_and_lint.yml
rony/module_templates/CI_workflows/CI/docker-compose.yml
rony/module_templates/CI_workflows/CI/scripts/apply.sh
rony/module_templates/CI_workflows/CI/scripts/build_and_push.sh
rony/module_templates/CI_workflows/CI/scripts/destroy.sh
rony/module_templates/CI_workflows/CI/scripts/format.sh
rony/module_templates/CI_workflows/CI/scripts/get_credentials.sh
rony/module_templates/CI_workflows/CI/scripts/plan.sh
rony/module_templates/CI_workflows/CI/scripts/pre_terraform.sh
rony/module_templates/CI_workflows/CI/scripts/test_and_lint.sh
rony/module_templates/CI_workflows/CI/scripts/validate_terraform.sh
rony/module_templates/__AWS_BASE__/.tpl.gitignore
rony/module_templates/__AWS_BASE__/README.tpl.md
rony/module_templates/__AWS_BASE__/CI/scripts/apply.sh
rony/module_templates/__AWS_BASE__/CI/scripts/destroy.sh
rony-0.3.2.dist-info/LICENSE
rony-0.3.2.dist-info/METADATA
rony-0.3.2.dist-info/WHEEL
rony-0.3.2.dist-info/entry_points.txt
rony-0.3.2.dist-info/top_level.txt
rony-0.3.2.dist-info/RECORD
