Metadata-Version: 2.1
Name: rony
Version: 0.3.2
Summary: An opinionated Data Engineering framework
Home-page: https://github.com/A3Data/rony
Author: A3Data
Author-email: rony@a3data.com.br
License: Apache License 2.0
Keywords: data engineering mlops devops pipelines
Classifier: Development Status :: 4 - Beta
Classifier: License :: OSI Approved :: Apache Software License
Classifier: Programming Language :: Python :: 3.6
Classifier: Programming Language :: Python :: 3.7
Classifier: Programming Language :: Python :: 3.8
Classifier: Topic :: Software Development
Requires-Python: >=3.6
License-File: LICENSE
Requires-Dist: Click (<8.0.0,>=7.0.0)
Requires-Dist: Jinja2 (<=3.1.2,>=3.0.0)
Requires-Dist: packaging (<=21.3,>=21.0)
Requires-Dist: unidiff (<=0.7.4,>=0.7.0)
